wqb/__init__.py
wqb/auto_auth_session.py
wqb/datetime_range.py
wqb/filter_range.py
wqb/wqb_session.py
wqb/wqb_urls.py
wqb-0.2.5.dist-info/LICENSE
wqb-0.2.5.dist-info/METADATA
wqb-0.2.5.dist-info/WHEEL
wqb-0.2.5.dist-info/top_level.txt
wqb-0.2.5.dist-info/RECORD
