Metadata-Version: 2.2
Name: wqb
Version: 0.2.5
Summary: A better machine lib.
Author-email: Rocky Haotian Du <rocky_d@yeah.net>
License: MIT License
Project-URL: repository, https://github.com/rocky-d/wqb
Classifier: Intended Audience :: Developers
Classifier: License :: OSI Approved :: MIT License
Classifier: Operating System :: OS Independent
Classifier: Programming Language :: Python :: 3
Classifier: Programming Language :: Python :: 3 :: Only
Classifier: Programming Language :: Python :: 3.11
Classifier: Programming Language :: Python :: 3.12
Classifier: Programming Language :: Python :: 3.13
Requires-Python: >=3.11
License-File: LICENSE
Requires-Dist: requests
